qbpm/__init__.py
qbpm/__main__.py
qbpm/choose.py
qbpm/config.py
qbpm/config.toml
qbpm/desktop.py
qbpm/launch.py
qbpm/log.py
qbpm/main.py
qbpm/menus.py
qbpm/paths.py
qbpm/profiles.py
qbpm/session.py
qbpm-2.4.dist-info/entry_points.txt
qbpm-2.4.dist-info/licenses/LICENSE
qbpm-2.4.dist-info/WHEEL
qbpm-2.4.dist-info/METADATA
qbpm-2.4.dist-info/RECORD
