Metadata-Version: 2.4
Name: qbpm
Version: 2.4
Summary: qutebrowser profile manager
Author-email: Peter Rice <peter@peterrice.xyz>
Requires-Python: >= 3.11
License-Expression: GPL-3.0-or-later
Classifier: Environment :: Console
Classifier: Intended Audience :: End Users/Desktop
Classifier: Operating System :: MacOS
Classifier: Operating System :: POSIX :: Linux
Classifier: Programming Language :: Python :: 3
Classifier: Typing :: Typed
License-File: LICENSE
Requires-Dist: click
Requires-Dist: xdg-base-dirs
Requires-Dist: dacite
Project-URL: changelog, https://github.com/pvsr/qbpm/blob/main/CHANGELOG.md
Project-URL: homepage, https://github.com/pvsr/qbpm
Project-URL: issues, https://github.com/pvsr/qbpm/issues
Project-URL: repository, https://github.com/pvsr/qbpm
